{
  "schemaVersion": 1,
  "module": {
    "path": "src/core",
    "name": "core",
    "purpose": "Core library and server binary crate package with workflow runtime, session server, and preprocess modules.",
    "changeStatus": "modified"
  },
  "modified": [
    ".",
    "config.json",
    "lib.rs",
    "main.rs",
    "model.rs",
    "runtime.rs",
    "transport.rs"
  ],
  "deleted": [
    "io.rs"
  ],
  "childModules": [
    {
      "path": "src/core/preprocess",
      "name": "preprocess",
      "purpose": "Core preprocessing module split into error, output, and preprocessor files."
    }
  ],
  "elements": [
    {
      "name": "ModelRequest",
      "type": "struct",
      "changeStatus": "modified",
      "codeSegments": [
        {
          "sourcePath": "src/core/model.rs",
          "lineStart": 4,
          "lineEnd": 7,
          "language": "rust"
        }
      ]
    },
    {
      "name": "ModelResponse",
      "type": "struct",
      "changeStatus": "modified",
      "codeSegments": [
        {
          "sourcePath": "src/core/model.rs",
          "lineStart": 10,
          "lineEnd": 12,
          "language": "rust"
        }
      ]
    },
    {
      "name": "ModelError",
      "type": "enum",
      "changeStatus": "modified",
      "codeSegments": [
        {
          "sourcePath": "src/core/model.rs",
          "lineStart": 15,
          "lineEnd": 17,
          "language": "rust"
        },
        {
          "sourcePath": "src/core/model.rs",
          "lineStart": 19,
          "lineEnd": 25,
          "language": "rust"
        },
        {
          "sourcePath": "src/core/model.rs",
          "lineStart": 27,
          "lineEnd": 27,
          "language": "rust"
        }
      ]
    },
    {
      "name": "ModelBackend",
      "type": "trait",
      "changeStatus": "modified",
      "codeSegments": [
        {
          "sourcePath": "src/core/model.rs",
          "lineStart": 29,
          "lineEnd": 31,
          "language": "rust"
        }
      ]
    },
    {
      "name": "RemoteModelBackend",
      "type": "trait",
      "changeStatus": "modified",
      "codeSegments": [
        {
          "sourcePath": "src/core/model.rs",
          "lineStart": 33,
          "lineEnd": 35,
          "language": "rust"
        }
      ]
    },
    {
      "name": "LocalModelBackend",
      "type": "trait",
      "changeStatus": "modified",
      "codeSegments": [
        {
          "sourcePath": "src/core/model.rs",
          "lineStart": 37,
          "lineEnd": 39,
          "language": "rust"
        }
      ]
    },
    {
      "name": "EchoModelBackend",
      "type": "struct",
      "changeStatus": "modified",
      "codeSegments": [
        {
          "sourcePath": "src/core/model.rs",
          "lineStart": 42,
          "lineEnd": 42,
          "language": "rust"
        },
        {
          "sourcePath": "src/core/model.rs",
          "lineStart": 44,
          "lineEnd": 50,
          "language": "rust"
        }
      ]
    },
    {
      "name": "AgentExecutionRequest",
      "type": "struct",
      "changeStatus": "modified",
      "codeSegments": [
        {
          "sourcePath": "src/core/runtime.rs",
          "lineStart": 9,
          "lineEnd": 12,
          "language": "rust"
        }
      ]
    },
    {
      "name": "AgentExecutionResponse",
      "type": "struct",
      "changeStatus": "modified",
      "codeSegments": [
        {
          "sourcePath": "src/core/runtime.rs",
          "lineStart": 15,
          "lineEnd": 17,
          "language": "rust"
        }
      ]
    },
    {
      "name": "AgentWorkflowStep",
      "type": "enum",
      "changeStatus": "modified",
      "codeSegments": [
        {
          "sourcePath": "src/core/runtime.rs",
          "lineStart": 20,
          "lineEnd": 28,
          "language": "rust"
        }
      ]
    },
    {
      "name": "AgentWorkflow",
      "type": "struct",
      "changeStatus": "modified",
      "codeSegments": [
        {
          "sourcePath": "src/core/runtime.rs",
          "lineStart": 31,
          "lineEnd": 33,
          "language": "rust"
        },
        {
          "sourcePath": "src/core/runtime.rs",
          "lineStart": 35,
          "lineEnd": 43,
          "language": "rust"
        }
      ]
    },
    {
      "name": "DEFAULT_AGENT_WORKFLOW",
      "type": "const",
      "changeStatus": "modified",
      "codeSegments": [
        {
          "sourcePath": "src/core/runtime.rs",
          "lineStart": 45,
          "lineEnd": 53,
          "language": "rust"
        }
      ]
    },
    {
      "name": "CoreError",
      "type": "enum",
      "changeStatus": "modified",
      "codeSegments": [
        {
          "sourcePath": "src/core/runtime.rs",
          "lineStart": 56,
          "lineEnd": 59,
          "language": "rust"
        },
        {
          "sourcePath": "src/core/runtime.rs",
          "lineStart": 61,
          "lineEnd": 65,
          "language": "rust"
        },
        {
          "sourcePath": "src/core/runtime.rs",
          "lineStart": 67,
          "lineEnd": 71,
          "language": "rust"
        },
        {
          "sourcePath": "src/core/runtime.rs",
          "lineStart": 73,
          "lineEnd": 80,
          "language": "rust"
        },
        {
          "sourcePath": "src/core/runtime.rs",
          "lineStart": 82,
          "lineEnd": 82,
          "language": "rust"
        }
      ]
    },
    {
      "name": "AgentCore",
      "type": "struct",
      "changeStatus": "modified",
      "codeSegments": [
        {
          "sourcePath": "src/core/runtime.rs",
          "lineStart": 85,
          "lineEnd": 88,
          "language": "rust"
        },
        {
          "sourcePath": "src/core/runtime.rs",
          "lineStart": 90,
          "lineEnd": 132,
          "language": "rust"
        }
      ]
    },
    {
      "name": "CliCoreTransport",
      "type": "trait",
      "changeStatus": "modified",
      "codeSegments": [
        {
          "sourcePath": "src/core/transport.rs",
          "lineStart": 5,
          "lineEnd": 8,
          "language": "rust"
        }
      ]
    },
    {
      "name": "PassthroughCliCoreTransport",
      "type": "struct",
      "changeStatus": "modified",
      "codeSegments": [
        {
          "sourcePath": "src/core/transport.rs",
          "lineStart": 11,
          "lineEnd": 11,
          "language": "rust"
        },
        {
          "sourcePath": "src/core/transport.rs",
          "lineStart": 13,
          "lineEnd": 21,
          "language": "rust"
        }
      ]
    },
    {
      "name": "ComputeModelTransport",
      "type": "trait",
      "changeStatus": "modified",
      "codeSegments": [
        {
          "sourcePath": "src/core/transport.rs",
          "lineStart": 23,
          "lineEnd": 26,
          "language": "rust"
        }
      ]
    },
    {
      "name": "PassthroughModelTransport",
      "type": "struct",
      "changeStatus": "modified",
      "codeSegments": [
        {
          "sourcePath": "src/core/transport.rs",
          "lineStart": 29,
          "lineEnd": 29,
          "language": "rust"
        },
        {
          "sourcePath": "src/core/transport.rs",
          "lineStart": 31,
          "lineEnd": 39,
          "language": "rust"
        }
      ]
    }
  ]
}
